force_relative_import/__init__.py
force_relative_import/enable_now.py
force_relative_import-0.0.1.dist-info/LICENSE
force_relative_import-0.0.1.dist-info/METADATA
force_relative_import-0.0.1.dist-info/WHEEL
force_relative_import-0.0.1.dist-info/top_level.txt
force_relative_import-0.0.1.dist-info/RECORD
